.DS_Store
gym_jiminy/common/__init__.py
gym_jiminy/common/py.typed
gym_jiminy/common/bases/__init__.py
gym_jiminy/common/bases/blocks.py
gym_jiminy/common/bases/compositions.py
gym_jiminy/common/bases/interfaces.py
gym_jiminy/common/bases/pipeline.py
gym_jiminy/common/bases/quantities.py
gym_jiminy/common/blocks/__init__.py
gym_jiminy/common/blocks/body_orientation_observer.py
gym_jiminy/common/blocks/deformation_estimator.py
gym_jiminy/common/blocks/mahony_filter.py
gym_jiminy/common/blocks/motor_safety_limit.py
gym_jiminy/common/blocks/proportional_derivative_controller.py
gym_jiminy/common/blocks/quantity_observer.py
gym_jiminy/common/compositions/__init__.py
gym_jiminy/common/compositions/generic.py
gym_jiminy/common/compositions/locomotion.py
gym_jiminy/common/compositions/mixin.py
gym_jiminy/common/envs/__init__.py
gym_jiminy/common/envs/generic.py
gym_jiminy/common/envs/locomotion.py
gym_jiminy/common/envs/internal/__init__.py
gym_jiminy/common/envs/internal/play.py
gym_jiminy/common/quantities/__init__.py
gym_jiminy/common/quantities/generic.py
gym_jiminy/common/quantities/locomotion.py
gym_jiminy/common/quantities/manager.py
gym_jiminy/common/quantities/transform.py
gym_jiminy/common/utils/__init__.py
gym_jiminy/common/utils/math.py
gym_jiminy/common/utils/misc.py
gym_jiminy/common/utils/pipeline.py
gym_jiminy/common/utils/spaces.py
gym_jiminy/common/wrappers/__init__.py
gym_jiminy/common/wrappers/flatten.py
gym_jiminy/common/wrappers/normalize.py
gym_jiminy/common/wrappers/observation_layout.py
gym_jiminy/common/wrappers/observation_stack.py
gym_jiminy/common/wrappers/scale.py
gym_jiminy-1.8.13.dist-info/METADATA
gym_jiminy-1.8.13.dist-info/WHEEL
gym_jiminy-1.8.13.dist-info/top_level.txt
gym_jiminy-1.8.13.dist-info/RECORD
