Metadata-Version: 2.2
Name: gym-jiminy
Version: 1.8.13
Summary: Python-native OpenAI Gym interface between Jiminy open-source simulator and Reinforcement Learning frameworks.
Home-page: https://github.com/duburcqa/jiminy
Download-URL: https://github.com/duburcqa/jiminy/archive/1.8.13.tar.gz
Author: Alexis Duburcq
Author-email: alexis.duburcq@gmail.com
Maintainer: Alexis Duburcq
License: MIT
Keywords: reinforcement-learning robotics gym jiminy
Classifier: Development Status :: 3 - Alpha
Classifier: Intended Audience :: Science/Research
Classifier: Topic :: Scientific/Engineering :: Artificial Intelligence
Classifier: Topic :: Software Development :: Libraries :: Python Modules
Classifier: License :: OSI Approved :: MIT License
Classifier: Programming Language :: Python :: 3.10
Classifier: Programming Language :: Python :: 3.11
Classifier: Programming Language :: Python :: 3.12
Classifier: Programming Language :: Python :: 3.13
Requires-Python: >=3.10,<3.14
Requires-Dist: jiminy-py~=1.8.13
Requires-Dist: h5py
Requires-Dist: numba>=0.56.0
Requires-Dist: gymnasium<1.1,>=0.28
Requires-Dist: typing_extensions>=4.1.0
Provides-Extra: zoo
Requires-Dist: gym-jiminy-zoo~=1.8.13; extra == "zoo"
Provides-Extra: toolbox
Requires-Dist: gym-jiminy-toolbox~=1.8.13; extra == "toolbox"
Provides-Extra: rllib
Requires-Dist: gym-jiminy-rllib~=1.8.13; extra == "rllib"
Provides-Extra: all
Requires-Dist: gym-jiminy-toolbox~=1.8.13; extra == "all"
Requires-Dist: gym-jiminy-rllib~=1.8.13; extra == "all"
Requires-Dist: gym-jiminy-zoo~=1.8.13; extra == "all"
Dynamic: author
Dynamic: author-email
Dynamic: classifier
Dynamic: download-url
Dynamic: home-page
Dynamic: keywords
Dynamic: license
Dynamic: maintainer
Dynamic: provides-extra
Dynamic: requires-dist
Dynamic: requires-python
Dynamic: summary
